subparse/__init__.py
subparse/lazydecorator.py
subparse-0.6.dist-info/LICENSE.txt
subparse-0.6.dist-info/METADATA
subparse-0.6.dist-info/WHEEL
subparse-0.6.dist-info/top_level.txt
subparse-0.6.dist-info/RECORD
