Metadata-Version: 2.1
Name: subparse
Version: 0.6
Summary: A command line helper library for extensible subcommands
Home-page: https://github.com/mmerickel/subparse
Author: Michael Merickel
Author-email: oss@m.merickel.org
License: MIT
Keywords: argparse,cli,commandline,subcommand
Classifier: Development Status :: 4 - Beta
Classifier: Intended Audience :: Developers
Classifier: License :: OSI Approved :: MIT License
Classifier: Environment :: Console
Classifier: Operating System :: OS Independent
Classifier: Programming Language :: Python
Classifier: Programming Language :: Python :: 3
Classifier: Programming Language :: Python :: 3.8
Classifier: Programming Language :: Python :: 3.9
Classifier: Programming Language :: Python :: 3.10
Requires-Python: >=3.8
License-File: LICENSE.txt
Provides-Extra: testing
Requires-Dist: pytest ; extra == 'testing'
Requires-Dist: pytest-cov ; extra == 'testing'
